supervisor_eventflapping/__init__.py
supervisor_eventflapping/exitedsendtonewrelic.py
supervisor_eventflapping/process_state_monitor.py
supervisor_eventflapping_2-2.0.dist-info/METADATA
supervisor_eventflapping_2-2.0.dist-info/WHEEL
supervisor_eventflapping_2-2.0.dist-info/top_level.txt
supervisor_eventflapping_2-2.0.dist-info/RECORD
