Metadata-Version: 2.1
Name: supervisor-eventflapping-2
Version: 2.0
Summary: Adds eventlistener to detect rapidly exited processes
Home-page: https://github.com/mightydok/supervisor-eventflapping
Author: Oleg Babushkin
Author-email: o.babushkin@city-mobil.ru
License: BSD
Platform: UNKNOWN
Classifier: Development Status :: 2 - Pre-Alpha
Classifier: Intended Audience :: Developers
Classifier: License :: OSI Approved :: BSD License
Classifier: Natural Language :: English
Classifier: Programming Language :: Python :: 2
Classifier: Programming Language :: Python :: 2.6
Classifier: Programming Language :: Python :: 2.7
Classifier: Programming Language :: Python :: 3
Classifier: Programming Language :: Python :: 3.2
Classifier: Programming Language :: Python :: 3.3
Requires-Dist: supervisor (==3.3.5)
Requires-Dist: requests (==2.21.0)
